{
  "response": [
    99,
    {
      "uid": 324395877,
      "first_name": "Жанполь",
      "last_name": "Марат",
      "photo_50": "http://assets.teenvogue.com/photos/58c703466b185d38dd28d29d/master/pass/Portrait%20Cara%20Delevingne.cpImg.868.jpg"
    },
    {
      "uid": 203148242,
      "first_name": "Никита",
      "last_name": "Жанполь",
      "photo_50": "http://assets.teenvogue.com/photos/58c703466b185d38dd28d29d/master/pass/Portrait%20Cara%20Delevingne.cpImg.868.jpg"
    },
    {
      "uid": 46966,
      "first_name": "Бегемот",
      "last_name": "Жанполь",
      "photo_50": "http://assets.teenvogue.com/photos/58c703466b185d38dd28d29d/master/pass/Portrait%20Cara%20Delevingne.cpImg.868.jpg"
    },
    {
      "uid": 5987,
      "first_name": "Жанполь",
      "last_name": "Дольский",
      "photo_50": "http://assets.teenvogue.com/photos/58c703466b185d38dd28d29d/master/pass/Portrait%20Cara%20Delevingne.cpImg.868.jpg"
    },
    {
      "uid": 418875120,
      "first_name": "Жанполь",
      "last_name": "Верилиян",
      "photo_50": "http://assets.teenvogue.com/photos/58c703466b185d38dd28d29d/master/pass/Portrait%20Cara%20Delevingne.cpImg.868.jpg"
    },
    {
      "uid": 386595807,
      "first_name": "Жанполь",
      "last_name": "Карлеон",
      "photo_50": "http://assets.teenvogue.com/photos/58c703466b185d38dd28d29d/master/pass/Portrait%20Cara%20Delevingne.cpImg.868.jpg"
    },
    {
      "uid": 246637121,
      "first_name": "Жанполь",
      "last_name": "Лишьён",
      "photo_50": "http://assets.teenvogue.com/photos/58c703466b185d38dd28d29d/master/pass/Portrait%20Cara%20Delevingne.cpImg.868.jpg"
    },
    {
      "uid": 213415828,
      "first_name": "Жанполь",
      "last_name": "Марат",
      "photo_50": "http://assets.teenvogue.com/photos/58c703466b185d38dd28d29d/master/pass/Portrait%20Cara%20Delevingne.cpImg.868.jpg"
    },
    {
      "uid": 418522331,
      "first_name": "Марат",
      "last_name": "Жанполь",
      "photo_50": "http://assets.teenvogue.com/photos/58c703466b185d38dd28d29d/master/pass/Portrait%20Cara%20Delevingne.cpImg.868.jpg"
    },
    {
      "uid": 340548919,
      "first_name": "Жанполь",
      "last_name": "Идрисов",
      "photo_50": "http://assets.teenvogue.com/photos/58c703466b185d38dd28d29d/master/pass/Portrait%20Cara%20Delevingne.cpImg.868.jpg"
    }
  ]
}